pandasai_databricks/__init__.py
pandasai_databricks-0.1.5.dist-info/METADATA
pandasai_databricks-0.1.5.dist-info/WHEEL
pandasai_databricks-0.1.5.dist-info/licenses/LICENSE
pandasai_databricks-0.1.5.dist-info/RECORD
