Metadata-Version: 2.4
Name: pandasai-databricks
Version: 0.1.5
Summary: Databricks connector integration for PandasAI
License: Proprietary
License-File: LICENSE
Author: Gabriele Venturi
Requires-Python: >=3.9,<3.12
Classifier: License :: Other/Proprietary License
Classifier: Programming Language :: Python :: 3
Classifier: Programming Language :: Python :: 3.9
Classifier: Programming Language :: Python :: 3.10
Classifier: Programming Language :: Python :: 3.11
Requires-Dist: databricks-sql-connector[sqlalchemy] (>=3.6.0,<4.0.0)
Requires-Dist: pandasai (>=3.0.0b4)
Requires-Dist: pandasai-sql (>=0.1.0,<0.2.0)
Requires-Dist: pyarrow (>=14.0.1,<19.0.0)
Project-URL: Documentation, https://docs.pandas-ai.com/v3/data-ingestion
Project-URL: Repository, https://github.com/sinaptik-ai/pandas-ai
